odoo_client_lib-2.0.0.dist-info/licenses/licence.txt
odoolib/__init__.py
odoolib/dates.py
odoolib/json2.py
odoolib/main.py
odoolib/rpc.py
odoolib/tools.py
odoo_client_lib-2.0.0.dist-info/METADATA
odoo_client_lib-2.0.0.dist-info/WHEEL
odoo_client_lib-2.0.0.dist-info/top_level.txt
odoo_client_lib-2.0.0.dist-info/RECORD
