Metadata-Version: 2.4
Name: odoo-client-lib
Version: 2.0.0
Summary: Odoo Client Library allows to easily interact with Odoo in Python.
Author: Stephane Wirtel, Nicolas Vanhoren
Author-email: Nicolas Seinlet <nse@odoo.com>
License-Expression: BSD-3-Clause
Keywords: odoo,library,communication,rpc,xml-rpc,net-rpc,xmlrpc,python,client,lib,web,service
Requires-Python: >=3.9
License-File: licence.txt
Requires-Dist: httpx
Dynamic: license-file
